sap/__init__.py
sap/profiles.py
sap/spectra.py
sap/trees.py
sap/utils.py
test/__init__.py
test/test_first.py
test/test_profiles.py
test/test_spectra.py
test/test_trees.py
test/test_utils.py
sap-1.0.0.dist-info/LICENSE
sap-1.0.0.dist-info/METADATA
sap-1.0.0.dist-info/WHEEL
sap-1.0.0.dist-info/top_level.txt
sap-1.0.0.dist-info/RECORD
