Metadata-Version: 2.1
Name: sap
Version: 1.0.0
Summary: Simple Attribute Profiles
Home-page: https://github.com/fguiotte/sap
Author: Florent Guiotte
Author-email: florent@guiotte.fr
Classifier: Programming Language :: Python :: 3
Classifier: License :: OSI Approved
Classifier: Operating System :: OS Independent
Requires-Python: >=3.8
License-File: LICENSE
Requires-Dist: numpy
Requires-Dist: higra
Requires-Dist: tqdm
Requires-Dist: matplotlib
